autonomous/__init__.py
autonomous/cli.py
autonomous/logger.py
autonomous/ai/__init__.py
autonomous/ai/audioagent.py
autonomous/ai/baseagent.py
autonomous/ai/imageagent.py
autonomous/ai/jsonagent.py
autonomous/ai/textagent.py
autonomous/ai/models/__init__.py
autonomous/ai/models/gemini.py
autonomous/ai/models/local_model.py
autonomous/ai/models/mock_model.py
autonomous/apis/version_control/GHCallbacks.py
autonomous/apis/version_control/GHOrganization.py
autonomous/apis/version_control/GHRepo.py
autonomous/apis/version_control/GHVersionControl.py
autonomous/apis/version_control/__init__.py
autonomous/auth/__init__.py
autonomous/auth/autoauth.py
autonomous/auth/github.py
autonomous/auth/google.py
autonomous/auth/user.py
autonomous/db/__init__.py
autonomous/db/common.py
autonomous/db/connection.py
autonomous/db/context_managers.py
autonomous/db/db_sync.py
autonomous/db/dereference.py
autonomous/db/document.py
autonomous/db/errors.py
autonomous/db/fields.py
autonomous/db/mongodb_support.py
autonomous/db/pymongo_support.py
autonomous/db/signals.py
autonomous/db/base/__init__.py
autonomous/db/base/common.py
autonomous/db/base/datastructures.py
autonomous/db/base/document.py
autonomous/db/base/fields.py
autonomous/db/base/metaclasses.py
autonomous/db/base/utils.py
autonomous/db/queryset/__init__.py
autonomous/db/queryset/base.py
autonomous/db/queryset/field_list.py
autonomous/db/queryset/manager.py
autonomous/db/queryset/queryset.py
autonomous/db/queryset/transform.py
autonomous/db/queryset/visitor.py
autonomous/model/autoattr.py
autonomous/model/automodel.py
autonomous/storage/__init__.py
autonomous/storage/imagestorage.py
autonomous/storage/localstorage.py
autonomous/taskrunner/__init__.py
autonomous/taskrunner/autotasks.py
autonomous/taskrunner/task_router.py
autonomous/utils/markdown.py
autonomous_app-0.3.48.dist-info/METADATA
autonomous_app-0.3.48.dist-info/WHEEL
autonomous_app-0.3.48.dist-info/top_level.txt
autonomous_app-0.3.48.dist-info/RECORD
