Metadata-Version: 2.4
Name: autonomous-app
Version: 0.3.48
Summary: Containerized application framework built on Flask with additional libraries and tools for rapid development of web applications.
Author-email: Steven A Moore <samoore@binghamton.edu>
Project-URL: homepage, https://github.com/Sallenmoore/autonomous
Classifier: Programming Language :: Python :: 3.12
Classifier: License :: OSI Approved :: MIT License
Classifier: Operating System :: OS Independent
Requires-Python: >=3.12
Requires-Dist: Flask
Requires-Dist: setuptools
Requires-Dist: python-dotenv
Requires-Dist: blinker
Requires-Dist: pymongo
Requires-Dist: PyGithub
Requires-Dist: pygit2
Requires-Dist: pillow
Requires-Dist: redis
Requires-Dist: jsmin
Requires-Dist: requests
Requires-Dist: gunicorn
Requires-Dist: Authlib
Requires-Dist: rq
Requires-Dist: ollama
Requires-Dist: google-genai
Requires-Dist: sentence-transformers
Requires-Dist: dateparser
Requires-Dist: python-slugify
Requires-Dist: pydub
